solarwatt_energymanager/__init__.py
solarwatt_energymanager/battery_converter_device.py
solarwatt_energymanager/device.py
solarwatt_energymanager/energy_manager.py
solarwatt_energymanager/energy_manager_data.py
solarwatt_energymanager/energy_manager_device.py
solarwatt_energymanager/ev_station_device.py
solarwatt_energymanager/location_device.py
solarwatt_energymanager/power_meter_device.py
solarwatt_energymanager/s0_counter_device.py
solarwatt_energymanager_py-1.4.1.dist-info/LICENSE
solarwatt_energymanager_py-1.4.1.dist-info/METADATA
solarwatt_energymanager_py-1.4.1.dist-info/WHEEL
solarwatt_energymanager_py-1.4.1.dist-info/top_level.txt
solarwatt_energymanager_py-1.4.1.dist-info/RECORD
