Metadata-Version: 2.2
Name: solarwatt-energymanager-py
Version: 1.4.1
Summary: Client to query the SOLARWATT EnergyManager.
Home-page: https://github.com/Mas2112/solarwatt-energymanager-py
Author: Masaru Shimizu
Author-email: mshimizu@gmail.com
Project-URL: Bug Tracker, https://github.com/Mas2112/solarwatt-energymanager-py/issues
Classifier: Programming Language :: Python :: 3
Classifier: License :: OSI Approved :: MIT License
Classifier: Operating System :: OS Independent
Requires-Python: >=3.6
License-File: LICENSE
Requires-Dist: aiohttp
